trypanalyzer/__init__.py
trypanalyzer/analyzers.py
trypanalyzer/data_handlers.py
trypanalyzer-0.1.2.dist-info/licenses/LICENSE
trypanalyzer-0.1.2.dist-info/METADATA
trypanalyzer-0.1.2.dist-info/WHEEL
trypanalyzer-0.1.2.dist-info/top_level.txt
trypanalyzer-0.1.2.dist-info/RECORD
